cq_editor/__init__.py
cq_editor/__main__.py
cq_editor/_version.py
cq_editor/cq_utils.py
cq_editor/cqe_run.py
cq_editor/icons.py
cq_editor/icons_res.py
cq_editor/main_window.py
cq_editor/mixins.py
cq_editor/preferences.py
cq_editor/utils.py
cq_editor/widgets/__init__.py
cq_editor/widgets/code_editor.py
cq_editor/widgets/console.py
cq_editor/widgets/cq_object_inspector.py
cq_editor/widgets/debugger.py
cq_editor/widgets/editor.py
cq_editor/widgets/log.py
cq_editor/widgets/object_tree.py
cq_editor/widgets/occt_widget.py
cq_editor/widgets/pyhighlight.py
cq_editor/widgets/traceback_viewer.py
cq_editor/widgets/viewer.py
cq_editor-0.6.2.dist-info/licenses/LICENSE
cq_editor-0.6.2.dist-info/METADATA
cq_editor-0.6.2.dist-info/WHEEL
cq_editor-0.6.2.dist-info/entry_points.txt
cq_editor-0.6.2.dist-info/top_level.txt
cq_editor-0.6.2.dist-info/RECORD
