Metadata-Version: 2.4
Name: CQ-editor
Version: 0.6.2
Summary: CadQuery plugin to create a mesh of an assembly with corresponding data
Author: CadQuery Developers
Maintainer: CadQuery Developers
License:                                  Apache License
Project-URL: Repository, https://github.com/CadQuery/CQ-editor.git
Project-URL: Bug Tracker, https://github.com/CadQuery/CQ-editor/issues
Keywords: cadquery,CAD,engineering,design
Classifier: Development Status :: 4 - Beta
Classifier: Programming Language :: Python
Requires-Python: <=3.14,>=3.10
License-File: LICENSE
Requires-Dist: cadquery
Requires-Dist: PyQt5
Requires-Dist: pyqtgraph
Requires-Dist: qtawesome==1.4.0
Requires-Dist: path
Requires-Dist: logbook
Requires-Dist: requests
Requires-Dist: qtconsole<5.7.0,>=5.5.1
Requires-Dist: packaging
Provides-Extra: test
Requires-Dist: pytest; extra == "test"
Requires-Dist: pluggy; extra == "test"
Requires-Dist: pytest-qt; extra == "test"
Requires-Dist: pytest-mock; extra == "test"
Requires-Dist: pytest-repeat; extra == "test"
Requires-Dist: pyvirtualdisplay; extra == "test"
Provides-Extra: dev
Requires-Dist: black; extra == "dev"
Dynamic: license-file
